cs/x.py
cs.x-20240630.dist-info/METADATA
cs.x-20240630.dist-info/WHEEL
cs.x-20240630.dist-info/top_level.txt
cs.x-20240630.dist-info/RECORD
